wiiss.py
wiiss-0.1.0.dist-info/LICENSE
wiiss-0.1.0.dist-info/METADATA
wiiss-0.1.0.dist-info/WHEEL
wiiss-0.1.0.dist-info/top_level.txt
wiiss-0.1.0.dist-info/RECORD
